django_zombodb/__init__.py
django_zombodb/admin_mixins.py
django_zombodb/apps.py
django_zombodb/base_indexes.py
django_zombodb/exceptions.py
django_zombodb/helpers.py
django_zombodb/indexes.py
django_zombodb/operations.py
django_zombodb/querysets.py
django_zombodb/serializers.py
django_zombodb/static/django_zombodb/js/hide_show_score.js
django_zombodb/templates/django_zombodb/base.html
django_zombodb-0.3.0.dist-info/DESCRIPTION.rst
django_zombodb-0.3.0.dist-info/METADATA
django_zombodb-0.3.0.dist-info/RECORD
django_zombodb-0.3.0.dist-info/WHEEL
django_zombodb-0.3.0.dist-info/metadata.json
django_zombodb-0.3.0.dist-info/top_level.txt
