Metadata-Version: 2.0
Name: django-zombodb
Version: 0.3.0
Summary: Easy Django integration with Elasticsearch through ZomboDB Postgres Extension
Home-page: https://github.com/vintasoftware/django-zombodb
Author: Flávio Juvenal
Author-email: flavio@vinta.com.br
License: UNKNOWN
Keywords: django-zombodb
Platform: UNKNOWN
Classifier: Development Status :: 4 - Beta
Classifier: Framework :: Django :: 2.0
Classifier: Framework :: Django :: 2.1
Classifier: Intended Audience :: Developers
Classifier: License :: OSI Approved :: MIT License
Classifier: Natural Language :: English
Classifier: Programming Language :: Python :: 3
Classifier: Programming Language :: Python :: 3.5
Classifier: Programming Language :: Python :: 3.6
Classifier: Programming Language :: Python :: 3.7
Requires-Dist: elasticsearch-dsl (>=6.3.1)
Requires-Dist: elasticsearch (>=6.3.1)
Requires-Dist: psycopg2 (>=2.7.7)
